{
  "items": [
     {
         "color": "#121eba",
         "description": "....",
         "name": "Mission Done",
         "createdBy": "Moshe",
         "id": "123",
         "createDate": "'Sat Jun 22 2024 18:17:02 GMT+0300 (Israel Daylight Time)'",
         "lastUpdate": "'Sat Jun 22 2024 18:17:02 GMT+0300 (Israel Daylight Time)'"
       },
       {
         "color": "#b33232",
         "description": "DLC out",
         "name": "Elden Ring",
         "createdBy": "Haim",
         "id": "132nkl2dnel",
         "createDate": "'Sat Jun 22 2024 18:17:02 GMT+0300 (Israel Daylight Time)'",
         "lastUpdate": "'Sat Jun 22 2024 18:17:02 GMT+0300 (Israel Daylight Time)'"
       },
       {
         "color": "#b33232",
         "description": "Portugal will win",
         "name": "Euro 2024",
         "createdBy": "Ido",
         "id": "asdk567m67",
         "createDate": "'Sat Jun 22 2024 18:17:02 GMT+0300 (Israel Daylight Time)'",
         "lastUpdate": "'Sat Jun 22 2024 18:17:02 GMT+0300 (Israel Daylight Time)'"
       },
       {
         "color": "#f64c2",
         "description": "Something....",
         "name": "Something",
         "createdBy": "Efrat",
         "id": "cmnccncn33r",
         "createDate": "'Sat Jun 22 2024 18:17:02 GMT+0300 (Israel Daylight Time)'",
         "lastUpdate": "'Sat Jun 22 2024 18:17:02 GMT+0300 (Israel Daylight Time)'"
       }
  ]   
 }